bottle_cors_plugin.py
bottle_cors_plugin-0.1.9.data/scripts/bottle_cors_plugin.py
bottle_cors_plugin-0.1.9.dist-info/LICENSE
bottle_cors_plugin-0.1.9.dist-info/METADATA
bottle_cors_plugin-0.1.9.dist-info/WHEEL
bottle_cors_plugin-0.1.9.dist-info/top_level.txt
bottle_cors_plugin-0.1.9.dist-info/RECORD
