Metadata-Version: 2.1
Name: bottle-cors-plugin
Version: 0.1.9
Summary: The easiest way to use cors on bottle
Home-page: UNKNOWN
Author: Alfonso Villalobos
Author-email: alfonso@codepeat.com
License: MIT
Platform: UNKNOWN
Classifier: Programming Language :: Python :: 3.7
Classifier: License :: OSI Approved :: MIT License
Classifier: Operating System :: OS Independent
Requires-Python: >=3.6
Requires-Dist: bottle (>=0.12)
